tsumiki/__init__.py
tsumiki/cmd.py
tsumiki/magic.py
tsumiki/static/css/highlight.css
tsumiki/template/column_style.tpl
tsumiki/template/columns.tpl
tsumiki/template/columns_style.tpl
tsumiki/template/section.tpl
tsumiki-0.0.3.dist-info/METADATA
tsumiki-0.0.3.dist-info/RECORD
tsumiki-0.0.3.dist-info/WHEEL
tsumiki-0.0.3.dist-info/entry_points.txt
tsumiki-0.0.3.dist-info/top_level.txt
