Metadata-Version: 2.1
Name: tsumiki
Version: 0.0.3
Summary: tsumiki is a markup language to process multiple columns.
Home-page: https://github.com/drillan/tsumiki
Author: driller
License: MIT
Platform: UNKNOWN
Classifier: Programming Language :: Python :: 3
Requires-Python: >=3.6
Requires-Dist: markdown (<3.0)
Requires-Dist: py-gfm
Requires-Dist: jinja2
Requires-Dist: jinja2schema
Requires-Dist: Click
